plover_phoenix_stenotype.py
plover_phoenix_stenotype-0.2.1.dist-info/LICENSE
plover_phoenix_stenotype-0.2.1.dist-info/METADATA
plover_phoenix_stenotype-0.2.1.dist-info/WHEEL
plover_phoenix_stenotype-0.2.1.dist-info/entry_points.txt
plover_phoenix_stenotype-0.2.1.dist-info/top_level.txt
plover_phoenix_stenotype-0.2.1.dist-info/zip-safe
plover_phoenix_stenotype-0.2.1.dist-info/RECORD
