Metadata-Version: 2.1
Name: plover-phoenix-stenotype
Version: 0.2.1
Summary: A stenotype system designed to be used together with the Phoenix dictionary.
Home-page: https://github.com/Volensia/plover_phoenix_stenotype
Author: Volensia
License: MIT
Keywords: plover plover_plugin
Platform: UNKNOWN
License-File: LICENSE
Requires-Dist: plover (>=4.0.0.dev10)
